vscp_type.py
pyvscptypes-0.0.11.data/data/my_data/data_file
pyvscptypes-0.0.11.dist-info/LICENSE
pyvscptypes-0.0.11.dist-info/LICENSE.txt
pyvscptypes-0.0.11.dist-info/METADATA
pyvscptypes-0.0.11.dist-info/WHEEL
pyvscptypes-0.0.11.dist-info/entry_points.txt
pyvscptypes-0.0.11.dist-info/top_level.txt
pyvscptypes-0.0.11.dist-info/RECORD
